ayanami_init/__init__.py
ayanami_init/cli.py
ayanami_init-1.1.0.dist-info/METADATA
ayanami_init-1.1.0.dist-info/WHEEL
ayanami_init-1.1.0.dist-info/entry_points.txt
ayanami_init-1.1.0.dist-info/RECORD
