Metadata-Version: 2.4
Name: ayanami-init
Version: 1.1.0
Summary: My simple init new project tool
Requires-Python: >=3.9
Requires-Dist: wrapt>=2.0.1
